mobikit/__init__.py
mobikit/exceptions.py
mobikit/operators.py
mobikit/utils.py
mobikit/config/__init__.py
mobikit/config/config.py
mobikit/demo/__init__.py
mobikit/demo/demo.py
mobikit/models/__init__.py
mobikit/models/models.py
mobikit/reference/column_dict.csv
mobikit/reference/constants.json
mobikit/reference/counties_national.csv
mobikit/workspaces/__init__.py
mobikit/workspaces/base.py
mobikit/workspaces/exceptions.py
mobikit/workspaces/create/__init__.py
mobikit/workspaces/create/base.py
mobikit/workspaces/load/__init__.py
mobikit/workspaces/load/base.py
mobikit/workspaces/load/query_builder.py
mobikit/workspaces/search/__init__.py
mobikit/workspaces/search/base.py
mobikit-0.7.2.dist-info/LICENSE
mobikit-0.7.2.dist-info/METADATA
mobikit-0.7.2.dist-info/WHEEL
mobikit-0.7.2.dist-info/top_level.txt
mobikit-0.7.2.dist-info/RECORD
