Metadata-Version: 2.1
Name: mobikit
Version: 0.7.2
Summary: Python data retrieval and analysis package for mobikit data
Home-page: UNKNOWN
Author: Mobikit Inc.
Author-email: devs@mobikit.io
License: UNKNOWN
Keywords: mobikit data analysis spatial mobility
Platform: UNKNOWN
Classifier: Programming Language :: Python :: 3
Classifier: License :: OSI Approved :: MIT License
Classifier: Operating System :: OS Independent
Requires-Python: >=3.6
Requires-Dist: pandas (>=0.24.2)
Requires-Dist: requests (>=2.21.0)
Requires-Dist: mobikit-utils (~=0.1.0)
